redis_extensions/__init__.py
redis_extensions/expires.py
redis_extensions/extensions_base.py
redis_extensions_base-4.1.6.dist-info/METADATA
redis_extensions_base-4.1.6.dist-info/WHEEL
redis_extensions_base-4.1.6.dist-info/top_level.txt
redis_extensions_base-4.1.6.dist-info/RECORD
