Metadata-Version: 2.1
Name: redis-extensions-base
Version: 4.1.6
Summary: Redis-extensions-base is a base collection of custom extensions for Redis-py.
Home-page: https://github.com/RedisClub/redis-extensions-py/tree/base+redis4.x
Author: Hackathon
Author-email: kimi.huang@brightcells.com
License: UNKNOWN
Keywords: Redis Extensions Base
Platform: UNKNOWN
Classifier: License :: OSI Approved :: BSD License
Classifier: Programming Language :: Python
Classifier: Programming Language :: Python :: 3
Classifier: Programming Language :: Python :: 3.7
Classifier: Programming Language :: Python :: 3.8
Classifier: Programming Language :: Python :: 3.9
Classifier: Programming Language :: Python :: 3.10
Classifier: Topic :: Software Development :: Libraries :: Python Modules
Requires-Dist: TimeConvert
Requires-Dist: redis (>=4.0.2)
Requires-Dist: shortuuid
